python_qinlingclient-5.1.1.dist-info/DESCRIPTION.rst
python_qinlingclient-5.1.1.dist-info/METADATA
python_qinlingclient-5.1.1.dist-info/RECORD
python_qinlingclient-5.1.1.dist-info/WHEEL
python_qinlingclient-5.1.1.dist-info/entry_points.txt
python_qinlingclient-5.1.1.dist-info/metadata.json
python_qinlingclient-5.1.1.dist-info/pbr.json
python_qinlingclient-5.1.1.dist-info/top_level.txt
qinlingclient/__init__.py
qinlingclient/client.py
qinlingclient/i18n.py
qinlingclient/utils.py
qinlingclient/version.py
qinlingclient/common/__init__.py
qinlingclient/common/base.py
qinlingclient/common/exceptions.py
qinlingclient/common/http.py
qinlingclient/osc/__init__.py
qinlingclient/osc/plugin.py
qinlingclient/osc/v1/__init__.py
qinlingclient/osc/v1/base.py
qinlingclient/osc/v1/function.py
qinlingclient/osc/v1/function_alias.py
qinlingclient/osc/v1/function_execution.py
qinlingclient/osc/v1/function_version.py
qinlingclient/osc/v1/function_worker.py
qinlingclient/osc/v1/job.py
qinlingclient/osc/v1/runtime.py
qinlingclient/osc/v1/webhook.py
qinlingclient/tests/__init__.py
qinlingclient/tests/unit/__init__.py
qinlingclient/tests/unit/base.py
qinlingclient/tests/unit/fakes.py
qinlingclient/tests/unit/osc/__init__.py
qinlingclient/tests/unit/osc/v1/__init__.py
qinlingclient/tests/unit/osc/v1/fakes.py
qinlingclient/tests/unit/osc/v1/test_function.py
qinlingclient/tests/unit/osc/v1/test_function_alias.py
qinlingclient/tests/unit/osc/v1/test_function_execution.py
qinlingclient/tests/unit/osc/v1/test_function_version.py
qinlingclient/tests/unit/osc/v1/test_function_worker.py
qinlingclient/tests/unit/osc/v1/test_job.py
qinlingclient/tests/unit/osc/v1/test_runtime.py
qinlingclient/tests/unit/osc/v1/test_webhook.py
qinlingclient/tests/unit/v1/__init__.py
qinlingclient/tests/unit/v1/test_client.py
qinlingclient/tests/unit/v1/test_function.py
qinlingclient/tests/unit/v1/test_function_alias.py
qinlingclient/tests/unit/v1/test_function_execution.py
qinlingclient/tests/unit/v1/test_function_version.py
qinlingclient/tests/unit/v1/test_function_worker.py
qinlingclient/tests/unit/v1/test_job.py
qinlingclient/tests/unit/v1/test_runtime.py
qinlingclient/tests/unit/v1/test_webhook.py
qinlingclient/v1/__init__.py
qinlingclient/v1/client.py
qinlingclient/v1/function.py
qinlingclient/v1/function_alias.py
