Metadata-Version: 2.0
Name: python-qinlingclient
Version: 5.1.1
Summary: python-qinlingclient
Home-page: https://docs.openstack.org/qinling/latest/
Author: OpenStack
Author-email: openstack-discuss@lists.openstack.org
License: Apache License, Version 2.0
Platform: UNKNOWN
Classifier: Development Status :: 4 - Beta
Classifier: Environment :: Console
Classifier: Environment :: OpenStack
Classifier: Intended Audience :: Developers
Classifier: Intended Audience :: Information Technology
Classifier: Intended Audience :: System Administrators
Classifier: License :: OSI Approved :: Apache Software License
Classifier: Operating System :: POSIX :: Linux
Classifier: Programming Language :: Python
Classifier: Programming Language :: Python :: 3
Classifier: Programming Language :: Python :: 3.6
Classifier: Programming Language :: Python :: 3.7
Classifier: Programming Language :: Python :: 3.8
Requires-Python: >=3.6
Requires-Dist: Babel (!=2.4.0,>=2.3.4)
Requires-Dist: PrettyTable (<0.8,>=0.7.2)
Requires-Dist: PyYAML (>=3.13)
Requires-Dist: iso8601 (>=0.1.11)
Requires-Dist: osc-lib (>=1.8.0)
Requires-Dist: oslo.i18n (>=3.15.3)
Requires-Dist: oslo.log (>=3.36.0)
Requires-Dist: oslo.serialization (!=2.19.1,>=2.18.0)
Requires-Dist: oslo.utils (>=3.33.0)
Requires-Dist: pbr (!=2.1.0,>=2.0.0)
Requires-Dist: python-keystoneclient (>=3.8.0)
Requires-Dist: python-openstackclient (>=3.12.0)
Requires-Dist: requests (>=2.14.2)
Requires-Dist: six (>=1.10.0)
